LICENSE.txt
MANIFEST.in
README.rst
setup.py
dontasq/__init__.py
dontasq/asq_binding.py
dontasq/monkey_patches.py
dontasq.egg-info/PKG-INFO
dontasq.egg-info/SOURCES.txt
dontasq.egg-info/dependency_links.txt
dontasq.egg-info/requires.txt
dontasq.egg-info/top_level.txt