Metadata-Version: 1.1
Name: dontasq
Version: 0.1
Summary: Extend built-in Python collections with LINQ-for-objects style methods
Home-page: https://github.com/borzunov/dontasq
Author: Alexander Borzunov
Author-email: borzunov.alexander@gmail.com
License: MIT
Keywords: LINQ
Platform: UNKNOWN
Classifier: Development Status :: 4 - Beta
Classifier: Programming Language :: Python
Classifier: Programming Language :: Python :: 2.6
Classifier: Programming Language :: Python :: 2.7
Classifier: Programming Language :: Python :: 3.2
Classifier: Programming Language :: Python :: 3.3
Classifier: Programming Language :: Python :: 3.4
Classifier: Programming Language :: Python :: 3.5
Classifier: Programming Language :: Python :: Implementation :: CPython
Classifier: Intended Audience :: Developers
Classifier: License :: OSI Approved :: MIT License
Classifier: Operating System :: OS Independent
Classifier: Topic :: Software Development :: Libraries :: Python Modules
